{
  "most_likely|paris|2026-05-27": {
    "bucket_label": "30°C",
    "first_seen": "2026-05-27T12:30:39.222957+01:00",
    "last_seen": "2026-05-27T12:30:39.222957+01:00",
    "count": 1
  },
  "most_likely|london|2026-05-28": {
    "bucket_label": "31°C or higher",
    "first_seen": "2026-05-27T12:00:42.628792+01:00",
    "last_seen": "2026-05-27T12:30:39.222957+01:00",
    "count": 7
  },
  "most_likely|london|2026-05-27": {
    "bucket_label": "26°C",
    "first_seen": "2026-05-27T12:05:31.092417+01:00",
    "last_seen": "2026-05-27T12:30:39.222957+01:00",
    "count": 6
  }
}