{
  "most_likely|london|2026-05-16": {
    "bucket_label": "14°C",
    "first_seen": "2026-05-16T08:10:25.094007+01:00",
    "last_seen": "2026-05-16T11:15:28.541582+01:00",
    "count": 38
  },
  "most_likely|paris|2026-05-16": {
    "bucket_label": "15°C",
    "first_seen": "2026-05-16T08:35:25.889725+01:00",
    "last_seen": "2026-05-16T11:10:30.724393+01:00",
    "count": 29
  },
  "max_edge|london|2026-05-16": {
    "bucket_label": "13°C",
    "first_seen": "2026-05-16T09:35:22.254965+01:00",
    "last_seen": "2026-05-16T11:15:28.541582+01:00",
    "count": 21
  }
}